geopic_tag_reader/__init__.py
geopic_tag_reader/camera.py
geopic_tag_reader/cameras.csv
geopic_tag_reader/i18n.py
geopic_tag_reader/main.py
geopic_tag_reader/model.py
geopic_tag_reader/py.typed
geopic_tag_reader/reader.py
geopic_tag_reader/sequence.py
geopic_tag_reader/writer.py
geopic_tag_reader/translations/geopic_tag_reader.pot
geopic_tag_reader/translations/ar/LC_MESSAGES/geopic_tag_reader.mo
geopic_tag_reader/translations/ar/LC_MESSAGES/geopic_tag_reader.po
geopic_tag_reader/translations/be/LC_MESSAGES/geopic_tag_reader.mo
geopic_tag_reader/translations/be/LC_MESSAGES/geopic_tag_reader.po
geopic_tag_reader/translations/br/LC_MESSAGES/geopic_tag_reader.mo
geopic_tag_reader/translations/br/LC_MESSAGES/geopic_tag_reader.po
geopic_tag_reader/translations/da/LC_MESSAGES/geopic_tag_reader.mo
geopic_tag_reader/translations/da/LC_MESSAGES/geopic_tag_reader.po
geopic_tag_reader/translations/de/LC_MESSAGES/geopic_tag_reader.mo
geopic_tag_reader/translations/de/LC_MESSAGES/geopic_tag_reader.po
geopic_tag_reader/translations/en/LC_MESSAGES/geopic_tag_reader.mo
geopic_tag_reader/translations/en/LC_MESSAGES/geopic_tag_reader.po
geopic_tag_reader/translations/eo/LC_MESSAGES/geopic_tag_reader.mo
geopic_tag_reader/translations/eo/LC_MESSAGES/geopic_tag_reader.po
geopic_tag_reader/translations/es/LC_MESSAGES/geopic_tag_reader.mo
geopic_tag_reader/translations/es/LC_MESSAGES/geopic_tag_reader.po
geopic_tag_reader/translations/fi/LC_MESSAGES/geopic_tag_reader.mo
geopic_tag_reader/translations/fi/LC_MESSAGES/geopic_tag_reader.po
geopic_tag_reader/translations/fr/LC_MESSAGES/geopic_tag_reader.mo
geopic_tag_reader/translations/fr/LC_MESSAGES/geopic_tag_reader.po
geopic_tag_reader/translations/hu/LC_MESSAGES/geopic_tag_reader.mo
geopic_tag_reader/translations/hu/LC_MESSAGES/geopic_tag_reader.po
geopic_tag_reader/translations/it/LC_MESSAGES/geopic_tag_reader.mo
geopic_tag_reader/translations/it/LC_MESSAGES/geopic_tag_reader.po
geopic_tag_reader-1.8.1.dist-info/entry_points.txt
geopic_tag_reader-1.8.1.dist-info/licenses/LICENSE
geopic_tag_reader-1.8.1.dist-info/WHEEL
geopic_tag_reader-1.8.1.dist-info/METADATA
geopic_tag_reader-1.8.1.dist-info/RECORD
