Metadata-Version: 2.4
Name: geopic-tag-reader
Version: 1.8.1
Summary: GeoPicTagReader
Author-email: Adrien PAVIE <panieravide@riseup.net>
Requires-Python: >=3.9
Classifier: License :: OSI Approved :: MIT License
License-File: LICENSE
Requires-Dist: typer ~= 0.15
Requires-Dist: xmltodict ~= 0.14
Requires-Dist: pyexiv2 == 2.15.3
Requires-Dist: timezonefinder == 6.5.9
Requires-Dist: pytz ~= 2025.2
Requires-Dist: types-pytz ~= 2025.2.0
Requires-Dist: types-python-dateutil ~= 2.9.0
Requires-Dist: rtree ~= 1.4.0
Requires-Dist: flit ~= 3.8.0 ; extra == "build"
Requires-Dist: black ~= 25.1.0 ; extra == "dev"
Requires-Dist: mypy ~= 1.15.0 ; extra == "dev"
Requires-Dist: pytest ~= 8.3.5 ; extra == "dev"
Requires-Dist: pytest-datafiles ~= 3.0 ; extra == "dev"
Requires-Dist: types-xmltodict ~= 0.14 ; extra == "dev"
Requires-Dist: pre-commit ~= 4.2 ; extra == "dev"
Requires-Dist: mkdocs-material ~= 9.6.11 ; extra == "docs"
Requires-Dist: mkdocstrings[python] ~= 0.29.1 ; extra == "docs"
Requires-Dist: python-dateutil ~= 2.9.0 ; extra == "write-exif"
Requires-Dist: types-python-dateutil ~= 2.9.0.20241003 ; extra == "write-exif"
Project-URL: Home, https://gitlab.com/panoramax/server/geo-picture-tag-reader
Provides-Extra: build
Provides-Extra: dev
Provides-Extra: docs
Provides-Extra: write-exif
